infrasys/__init__.py
infrasys/arrow_storage.py
infrasys/base_quantity.py
infrasys/chronify_time_series_storage.py
infrasys/common.py
infrasys/component.py
infrasys/component_associations.py
infrasys/component_manager.py
infrasys/cost_curves.py
infrasys/exceptions.py
infrasys/function_data.py
infrasys/h5_time_series_storage.py
infrasys/id_manager.py
infrasys/in_memory_time_series_storage.py
infrasys/location.py
infrasys/loggers.py
infrasys/migrations/__init__.py
infrasys/migrations/db_migrations.py
infrasys/migrations/metadata_migration.py
infrasys/models.py
infrasys/normalization.py
infrasys/pint_quantities.py
infrasys/py.typed
infrasys/quantities.py
infrasys/serialization.py
infrasys/supplemental_attribute.py
infrasys/supplemental_attribute_associations.py
infrasys/supplemental_attribute_manager.py
infrasys/system.py
infrasys/time_series_manager.py
infrasys/time_series_metadata_store.py
infrasys/time_series_models.py
infrasys/time_series_storage_base.py
infrasys/utils/__init__.py
infrasys/utils/classes.py
infrasys/utils/h5_utils.py
infrasys/utils/metadata_utils.py
infrasys/utils/path_utils.py
infrasys/utils/sqlite.py
infrasys/utils/time_utils.py
infrasys/value_curves.py
infrasys-1.0.1.dist-info/WHEEL
infrasys-1.0.1.dist-info/METADATA
infrasys-1.0.1.dist-info/RECORD
