Metadata-Version: 2.4
Name: infrasys
Version: 1.0.1
Summary: 
Keywords: infrastructure,time-series,energy,grid,data-storage
Author: Aadil Latif, Daniel Thom, Kapil Duwadi, Pedro Andres Sanchez Perez, Tarek Elgindy
Author-email: Aadil Latif <aadil.latif@nrel.gov>, Daniel Thom <daniel.thom@nrel.gov>, Kapil Duwadi <kapil.duwadi@nrel.gov>, Pedro Andres Sanchez Perez <pesap@users.noreply.github.com>, Tarek Elgindy <tarek.elgindy@nrel.gov>
License-Expression: BSD-3-Clause
Classifier: Development Status :: 5 - Production/Stable
Classifier: Programming Language :: Python
Classifier: Programming Language :: Python :: 3.10
Classifier: Programming Language :: Python :: 3.11
Classifier: Programming Language :: Python :: 3.12
Classifier: Programming Language :: Python :: 3.13
Classifier: Programming Language :: Python :: Implementation :: CPython
Classifier: Programming Language :: Python :: Implementation :: PyPy
Requires-Dist: h5py>=3.13,<4
Requires-Dist: loguru>=0.7,<0.8
Requires-Dist: numpy>=2,<3
Requires-Dist: orjson>=3.11.5,<4
Requires-Dist: pandas>=2,<3
Requires-Dist: pint~=0.23
Requires-Dist: pyarrow>=21,<23
Requires-Dist: pydantic>=2.12,<3
Requires-Dist: python-dateutil>=2.9,<3
Requires-Dist: rich>=13.7,<14
Requires-Dist: chronify~=0.6.0 ; extra == 'chronify'
Requires-Python: >=3.11, <3.14
Project-URL: Documentation, https://github.com/NREL/infrasys#readme
Project-URL: Issues, https://github.com/NREL/infrasys/issues
Project-URL: Source, https://github.com/NREL/infrasys
Provides-Extra: chronify
